googletrans/__init__.py
googletrans/client.py
googletrans/constants.py
googletrans/gtoken.py
googletrans/models.py
googletrans/urls.py
googletrans/utils.py
googletrans_modified-1.1.1.data/scripts/translate
googletrans_modified-1.1.1.dist-info/LICENSE
googletrans_modified-1.1.1.dist-info/METADATA
googletrans_modified-1.1.1.dist-info/WHEEL
googletrans_modified-1.1.1.dist-info/top_level.txt
googletrans_modified-1.1.1.dist-info/RECORD
