Metadata-Version: 2.1
Name: googletrans-modified
Version: 1.1.1
Summary: Free Google Translate API for Python. Translates totally free of charge.
Home-page: https://github.com/HaykSerobyan-89/py-googletrans-modified
Author: Hayk Serobyan
Author-email: hayk.serobyan.89@gmail.com
License: MIT
Keywords: google translate translator
Classifier: Operating System :: POSIX
Classifier: Operating System :: Microsoft :: Windows
Classifier: Operating System :: MacOS :: MacOS X
Classifier: Programming Language :: Python
Classifier: Programming Language :: Python :: 3.6
Classifier: Programming Language :: Python :: 3.7
Classifier: Programming Language :: Python :: 3.8
Classifier: Programming Language :: Python :: 3.9
Classifier: Programming Language :: Python :: 3.10
Classifier: Programming Language :: Python :: 3.11
Classifier: Programming Language :: Python :: 3.12
Classifier: Programming Language :: Python :: 3.13
Requires-Python: >=3.6
License-File: LICENSE
Requires-Dist: httpx[http2]>=0.23
